proxbox_api/__init__.py
proxbox_api/cache.py
proxbox_api/exception.py
proxbox_api/logger.py
proxbox_api/main.py
proxbox_api/diode/diode.py
proxbox_api/enum/proxmox.py
proxbox_api/enum/netbox/__init__.py
proxbox_api/enum/netbox/dcim/__init__.py
proxbox_api/enum/netbox/virtualization/__init__.py
proxbox_api/routes/__init__.py
proxbox_api/routes/netbox/__init__.py
proxbox_api/routes/proxbox/__init__.py
proxbox_api/routes/proxbox/clusters/__init__.py
proxbox_api/routes/proxmox/__init__.py
proxbox_api/routes/proxmox/cluster.py
proxbox_api/routes/proxmox/nodes.py
proxbox_api/schemas/__init__.py
proxbox_api/schemas/proxmox.py
proxbox_api/schemas/netbox/__init__.py
proxbox_api/schemas/netbox/dcim/__init__.py
proxbox_api/schemas/netbox/extras/__init__.py
proxbox_api/schemas/netbox/virtualization/__init__.py
proxbox_api/session/netbox.py
proxbox_api/session/proxmox.py
proxbox_api-0.0.2.post3.dist-info/licenses/LICENSE
proxbox_api-0.0.2.post3.dist-info/METADATA
proxbox_api-0.0.2.post3.dist-info/WHEEL
proxbox_api-0.0.2.post3.dist-info/top_level.txt
proxbox_api-0.0.2.post3.dist-info/RECORD
