Metadata-Version: 2.4
Name: proxbox_api
Version: 0.0.2.post3
Summary: Proxbox API service made using FastAPI
Requires-Python: >=3.10
License-File: LICENSE
Requires-Dist: fastapi[standard]>=0.115.6
Requires-Dist: proxmoxer>=2.2.0
Requires-Dist: pynetbox>=7.4.1
Requires-Dist: pynetbox-api==0.0.2.post1
Requires-Dist: sqlmodel>=0.0.22
Dynamic: license-file
